{
    "frases_motivacionales": [
      {
        "pelicula": "Star Wars",
        "frase": "Que la fuerza te acompañe."
      },
      {
        "pelicula": "Rocky",
        "frase": "¡No se trata de qué tan fuerte golpeas, se trata de qué tan fuerte puedes ser golpeado y seguir adelante!"
      },
      {
        "pelicula": "El señor de los anillos",
        "frase": "Incluso la persona más pequeña puede cambiar el curso del futuro."
      },
      {
        "pelicula": "Matrix",
        "frase": "No intentes doblar la cuchara. Eso es imposible. En su lugar, sólo intenta darte cuenta de la verdad."
      },
      {
        "pelicula": "Forrest Gump",
        "frase": "La vida es como una caja de chocolates, nunca sabes lo que te va a tocar."
      },
      {
        "pelicula": "El rey león",
        "frase": "Recuerda quién eres."
      },
      {
        "pelicula": "En busca de la felicidad",
        "frase": "No permitas que nadie diga que no puedes hacer algo. Si tienes un sueño, ve por él."
      },
      {
        "pelicula": "Ratatouille",
        "frase": "Cualquiera puede cocinar, pero sólo el intrépido puede ser grande."
      },
      {
        "pelicula": "Mujer bonita",
        "frase": "Toma riesgos y haz lo inesperado."
      },
      {
        "pelicula": "El club de la pelea",
        "frase": "No eres tu trabajo. No eres cuánto tienes en el banco. No eres el auto que manejas. No eres el contenido de tu billetera."
      },
      {
        "pelicula": "Frozen",
        "frase": "Déjalo ir y déjalo brillar."
      },
      {
        "pelicula": "El diablo viste a la moda",
        "frase": "La vida es demasiado corta para vestir ropa aburrida."
      },
      {
        "pelicula": "El indomable Will Hunting",
        "frase": "Tu no tienes la menor idea de lo que es tener alguien mirándote a los ojos y estar completamente desarmado."
      },
      {
        "pelicula": "Braveheart",
        "frase": "Cada hombre muere, pero no cada hombre realmente vive."
      },
      {
        "pelicula": "Mulan",
        "frase": "La flor que florece en la adversidad es la más rara y hermosa de todas."
      },
      {
        "pelicula": "Cadena perpetua",
        "frase": "La esperanza es una buena cosa, quizás la mejor de todas, y las cosas buenas nunca mueren."
      },
      {
        "pelicula": "El discurso del rey",
        "frase": "No se trata de cómo caes, se trata de cómo te levantas."
      },
      {
        "pelicula": "Up",
        "frase": "La aventura está ahí afuera."
      },
      {
        "pelicula": "Spider-Man: Un nuevo universo",
        "frase": "Cualquiera puede usar la máscara. Puedes llevar esta máscara."
      },
      {
        "pelicula": "El gran Lebowski",
        "frase": "A veces, hay un hombre, bien, es el hombre para su tiempo y lugar. Encaja bien, como su guante."
      },
      {
        "pelicula": "El club de los poetas muertos",
        "frase": "Carpe Diem. Aprovecha el día, chicos. Hagan de sus vidas algo extraordinario."
      },
      {
        "pelicula": "El lobo de Wall Street",
        "frase": "El único límite para el impacto de mañana es la creatividad de hoy."
      },
      {
        "pelicula": "El curioso caso de Benjamin Button",
        "frase": "Nunca es demasiado tarde, o demasiado pronto, para ser quien quieres ser."
      },
      {
        "pelicula": "El padrino",
        "frase": "Mantén a tus amigos cerca y a tus enemigos más cerca."
      },
      {
        "pelicula": "Amélie",
        "frase": "Es mejor ayudar a la gente que esperar que alguien lo haga por ti."
      },
      {
        "pelicula": "El gran dictador",
        "frase": "La vida puede ser maravillosa si no se le tiene miedo."
      },
      {
        "pelicula": "El renacido",
        "frase": "A veces tienes que hacer cosas que odias para poder sobrevivir."
      },
      {
        "pelicula": "El club de las desmadrosas",
        "frase": "¡Vive con pasión!"
      },
      {
        "pelicula": "Los juegos del hambre",
        "frase": "Recuerda quién eres y de dónde vienes."
      },
      {
        "pelicula": "Interestelar",
        "frase": "No hay lugar como el hogar."
      },
      {
        "pelicula": "El secreto de sus ojos",
      "frase": "Un buen juez es aquel a quien la ley inspira miedo."
      },
      {
        "pelicula": "Los increíbles",
        "frase": "A veces, hacer lo correcto suena como hacer lo incorrecto."
      },
      {
        "pelicula": "El luchador",
        "frase": "Tienes que estar dispuesto a recibir el golpe y seguir adelante."
      },
      {
        "pelicula": "El gran hotel Budapest",
        "frase": "No te preocupes, solo sé tú mismo."
      },
      {
        "pelicula": "El viaje de Chihiro",
        "frase": "No llores ante las desgracias, las desgracias no son eternas."
      },
      {
        "pelicula": "El niño con el pijama de rayas",
        "frase": "A veces, el futuro está justo delante de nosotros."
      },
      {
        "pelicula": "El pianista",
        "frase": "La música es un regalo, y regalos como éste no pueden ser rechazados."
      },
      {
        "pelicula": "Gladiador",
        "frase": "Lo que hacemos en la vida, tiene eco en la eternidad."
      },
      {
        "pelicula": "La La Land",
        "frase": "Aquí está a los que sueñan, los inquietos, los emocionales. ¡Aquí está a los locos!"
      },
      {
        "pelicula": "El discurso del rey",
        "frase": "A veces, el silencio es la cosa más elocuente."
      },
      {
        "pelicula": "El club de los cinco",
        "frase": "No medimos el tiempo, medimos la vida."
      },
      {
        "pelicula": "Coco",
        "frase": "La familia es todo."
      },
      {
        "pelicula": "El lado bueno de las cosas",
        "frase": "La felicidad no es constante. Eso es algo que todos tenemos que aprender."
      },
      {
        "pelicula": "Interestelar",
        "frase": "El amor es la única cosa que trasciende el tiempo y el espacio."
      },
      {
        "pelicula": "La red social",
        "frase": "Las conexiones que haces en la mente de alguien son mucho más importantes que las que haces en un servidor."
      },
      {
        "pelicula": "El gran Gatsby",
        "frase": "No se puede repetir el pasado."
      },
      {
        "pelicula": "Jurassic Park",
        "frase": "La vida se abre camino."
      }
    ]
}  